{
  "annotations": {
    "list": [
      {
        "builtIn": 1,
        "datasource": "-- Grafana --",
        "enable": true,
        "hide": true,
        "iconColor": "rgba(0, 211, 255, 1)",
        "name": "Annotations & Alerts",
        "target": {
          "limit": 100,
          "matchAny": false,
          "tags": [],
          "type": "dashboard"
        },
        "type": "dashboard"
      }
    ]
  },
  "description": "",
  "editable": false,
  "fiscalYearStartMonth": 0,
  "graphTooltip": 0,
  "id": null,
  "links": [],
  "liveNow": false,
  "panels": [
    {
      "collapsed": false,
      "gridPos": {
        "h": 1,
        "w": 24,
        "x": 0,
        "y": 0
      },
      "id": 298,
      "panels": [],
      "title": "Alerts",
      "type": "row"
    },
    {
      "datasource": {
        "type": "prometheus",
        "uid": "${datasource}"
      },
      "description": "",
      "fieldConfig": {
        "defaults": {
          "color": {
            "mode": "thresholds"
          },
          "mappings": [],
          "thresholds": {
            "mode": "absolute",
            "steps": [
              {
                "color": "green",
                "value": null
              },
              {
                "color": "red",
                "value": 1
              }
            ]
          }
        },
        "overrides": []
      },
      "gridPos": {
        "h": 8,
        "w": 4,
        "x": 0,
        "y": 1
      },
      "id": 306,
      "options": {
        "colorMode": "value",
        "graphMode": "area",
        "justifyMode": "auto",
        "orientation": "auto",
        "reduceOptions": {
          "calcs": [
            "lastNotNull"
          ],
          "fields": "",
          "values": false
        },
        "textMode": "auto"
      },
      "pluginVersion": "8.4.2",
      "targets": [
        {
          "datasource": {
            "type": "prometheus",
            "uid": "$datasource"
          },
          "exemplar": true,
          "expr": "sum(\n    ALERTS{alertstate=\"firing\",cluster_name=~\"$cluster_name\",category=~\"$category\",severity=~\"$severity\"}\n    or\n    ALERTS{alertstate=\"firing\",instance=~\"$node\",category=~\"$category\",severity=~\"$severity\"}\n)",
          "instant": false,
          "interval": "",
          "legendFormat": "Alerts",
          "refId": "A"
        }
      ],
      "title": "Active Alerts",
      "type": "stat"
    },
    {
      "datasource": {
        "type": "prometheus",
        "uid": "${datasource}"
      },
      "description": "",
      "fieldConfig": {
        "defaults": {
          "color": {
            "mode": "thresholds"
          },
          "mappings": [],
          "noValue": "0",
          "thresholds": {
            "mode": "absolute",
            "steps": [
              {
                "color": "green",
                "value": null
              },
              {
                "color": "yellow",
                "value": 1
              }
            ]
          }
        },
        "overrides": []
      },
      "gridPos": {
        "h": 8,
        "w": 4,
        "x": 4,
        "y": 1
      },
      "id": 308,
      "options": {
        "colorMode": "value",
        "graphMode": "none",
        "justifyMode": "auto",
        "orientation": "auto",
        "reduceOptions": {
          "calcs": [
            "lastNotNull"
          ],
          "fields": "",
          "values": false
        },
        "textMode": "auto"
      },
      "pluginVersion": "8.4.2",
      "targets": [
        {
          "datasource": {
            "type": "prometheus",
            "uid": "$datasource"
          },
          "exemplar": false,
          "expr": "sum(\n    ALERTS{alertstate=\"pending\",cluster_name=~\"$cluster_name\",category=~\"$category\",severity=~\"$severity\"}\n    or\n    ALERTS{alertstate=\"pending\",instance=~\"$node\",category=~\"$category\",severity=~\"$severity\"}\n)",
          "instant": true,
          "interval": "",
          "legendFormat": "Alerts",
          "refId": "A"
        }
      ],
      "title": "Pending Alerts",
      "type": "stat"
    },
    {
      "datasource": {
        "type": "prometheus",
        "uid": "${datasource}"
      },
      "description": "",
      "fieldConfig": {
        "defaults": {
          "color": {
            "mode": "palette-classic"
          },
          "custom": {
            "hideFrom": {
              "legend": false,
              "tooltip": false,
              "viz": false
            }
          },
          "mappings": []
        },
        "overrides": []
      },
      "gridPos": {
        "h": 8,
        "w": 4,
        "x": 8,
        "y": 1
      },
      "id": 300,
      "options": {
        "displayLabels": [
          "percent"
        ],
        "legend": {
          "displayMode": "hidden",
          "placement": "bottom"
        },
        "pieType": "pie",
        "reduceOptions": {
          "calcs": [
            "lastNotNull"
          ],
          "fields": "",
          "values": false
        },
        "tooltip": {
          "mode": "single",
          "sort": "none"
        }
      },
      "targets": [
        {
          "datasource": {
            "type": "prometheus",
            "uid": "$datasource"
          },
          "exemplar": false,
          "expr": "count(\n    ALERTS{alertstate=\"firing\",cluster_name=~\"$cluster_name\",category=~\"$category\",severity=~\"$severity\"}\n    or\n    ALERTS{alertstate=\"firing\",instance=~\"$node\",category=~\"$category\",severity=~\"$severity\"}\n) by (alertname)",
          "instant": true,
          "interval": "",
          "legendFormat": "{{alertname}}",
          "refId": "A"
        }
      ],
      "title": "Active Alerts by Type",
      "type": "piechart"
    },
    {
      "datasource": {
        "type": "prometheus",
        "uid": "${datasource}"
      },
      "description": "",
      "fieldConfig": {
        "defaults": {
          "color": {
            "mode": "palette-classic"
          },
          "custom": {
            "hideFrom": {
              "legend": false,
              "tooltip": false,
              "viz": false
            }
          },
          "mappings": []
        },
        "overrides": [
          {
            "matcher": {
              "id": "byName",
              "options": "info"
            },
            "properties": [
              {
                "id": "color",
                "value": {
                  "fixedColor": "blue",
                  "mode": "fixed"
                }
              },
              {
                "id": "displayName",
                "value": "Info"
              }
            ]
          },
          {
            "matcher": {
              "id": "byName",
              "options": "warning"
            },
            "properties": [
              {
                "id": "color",
                "value": {
                  "fixedColor": "yellow",
                  "mode": "fixed"
                }
              },
              {
                "id": "displayName",
                "value": "Warning"
              }
            ]
          },
          {
            "matcher": {
              "id": "byName",
              "options": "critical"
            },
            "properties": [
              {
                "id": "displayName",
                "value": "Critical"
              },
              {
                "id": "color",
                "value": {
                  "fixedColor": "red",
                  "mode": "fixed"
                }
              }
            ]
          }
        ]
      },
      "gridPos": {
        "h": 8,
        "w": 4,
        "x": 12,
        "y": 1
      },
      "id": 301,
      "options": {
        "displayLabels": [
          "percent"
        ],
        "legend": {
          "displayMode": "hidden",
          "placement": "bottom"
        },
        "pieType": "pie",
        "reduceOptions": {
          "calcs": [
            "lastNotNull"
          ],
          "fields": "",
          "values": false
        },
        "tooltip": {
          "mode": "single",
          "sort": "none"
        }
      },
      "targets": [
        {
          "datasource": {
            "type": "prometheus",
            "uid": "$datasource"
          },
          "exemplar": false,
          "expr": "count(\n    ALERTS{alertstate=\"firing\",cluster_name=~\"$cluster_name\",category=~\"$category\",severity=~\"$severity\"}\n    or\n    ALERTS{alertstate=\"firing\",instance=~\"$node\",category=~\"$category\",severity=~\"$severity\"}\n) by (severity)",
          "instant": true,
          "interval": "",
          "legendFormat": "{{alertname}}",
          "refId": "A"
        }
      ],
      "title": "Active Alerts by Severity",
      "type": "piechart"
    },
    {
      "datasource": {
        "type": "prometheus",
        "uid": "${datasource}"
      },
      "description": "",
      "fieldConfig": {
        "defaults": {
          "color": {
            "mode": "palette-classic"
          },
          "custom": {
            "hideFrom": {
              "legend": false,
              "tooltip": false,
              "viz": false
            }
          },
          "mappings": []
        },
        "overrides": [
          {
            "matcher": {
              "id": "byName",
              "options": "info"
            },
            "properties": [
              {
                "id": "color",
                "value": {
                  "fixedColor": "blue",
                  "mode": "fixed"
                }
              },
              {
                "id": "displayName",
                "value": "Info"
              }
            ]
          },
          {
            "matcher": {
              "id": "byName",
              "options": "warning"
            },
            "properties": [
              {
                "id": "color",
                "value": {
                  "fixedColor": "yellow",
                  "mode": "fixed"
                }
              },
              {
                "id": "displayName",
                "value": "Warning"
              }
            ]
          },
          {
            "matcher": {
              "id": "byName",
              "options": "critical"
            },
            "properties": [
              {
                "id": "displayName",
                "value": "Critical"
              },
              {
                "id": "color",
                "value": {
                  "fixedColor": "red",
                  "mode": "fixed"
                }
              }
            ]
          }
        ]
      },
      "gridPos": {
        "h": 8,
        "w": 4,
        "x": 16,
        "y": 1
      },
      "id": 304,
      "options": {
        "displayLabels": [
          "percent"
        ],
        "legend": {
          "displayMode": "hidden",
          "placement": "bottom"
        },
        "pieType": "pie",
        "reduceOptions": {
          "calcs": [
            "lastNotNull"
          ],
          "fields": "",
          "values": false
        },
        "tooltip": {
          "mode": "single",
          "sort": "none"
        }
      },
      "targets": [
        {
          "datasource": {
            "type": "prometheus",
            "uid": "$datasource"
          },
          "exemplar": false,
          "expr": "count(\n    ALERTS{alertstate=\"firing\",cluster_name=~\"$cluster_name\",category=~\"$category\",severity=~\"$severity\"}\n    or\n    ALERTS{alertstate=\"firing\",instance=~\"$node\",category=~\"$category\",severity=~\"$severity\"}\n) by (category)",
          "instant": true,
          "interval": "",
          "legendFormat": "{{alertname}}",
          "refId": "A"
        }
      ],
      "title": "Active Alerts by Category",
      "type": "piechart"
    },
    {
      "datasource": {
        "type": "prometheus",
        "uid": "${datasource}"
      },
      "description": "",
      "fieldConfig": {
        "defaults": {
          "color": {
            "mode": "palette-classic"
          },
          "custom": {
            "hideFrom": {
              "legend": false,
              "tooltip": false,
              "viz": false
            }
          },
          "mappings": []
        },
        "overrides": [
          {
            "matcher": {
              "id": "byName",
              "options": "info"
            },
            "properties": [
              {
                "id": "color",
                "value": {
                  "fixedColor": "blue",
                  "mode": "fixed"
                }
              },
              {
                "id": "displayName",
                "value": "Info"
              }
            ]
          },
          {
            "matcher": {
              "id": "byName",
              "options": "warning"
            },
            "properties": [
              {
                "id": "color",
                "value": {
                  "fixedColor": "yellow",
                  "mode": "fixed"
                }
              },
              {
                "id": "displayName",
                "value": "Warning"
              }
            ]
          },
          {
            "matcher": {
              "id": "byName",
              "options": "critical"
            },
            "properties": [
              {
                "id": "displayName",
                "value": "Critical"
              },
              {
                "id": "color",
                "value": {
                  "fixedColor": "red",
                  "mode": "fixed"
                }
              }
            ]
          }
        ]
      },
      "gridPos": {
        "h": 8,
        "w": 4,
        "x": 20,
        "y": 1
      },
      "id": 305,
      "options": {
        "displayLabels": [
          "percent"
        ],
        "legend": {
          "displayMode": "hidden",
          "placement": "bottom"
        },
        "pieType": "pie",
        "reduceOptions": {
          "calcs": [
            "lastNotNull"
          ],
          "fields": "",
          "values": false
        },
        "tooltip": {
          "mode": "single",
          "sort": "none"
        }
      },
      "targets": [
        {
          "datasource": {
            "type": "prometheus",
            "uid": "$datasource"
          },
          "exemplar": false,
          "expr": "count(\n    ALERTS{alertstate=\"firing\",cluster_name=~\"$cluster_name\",category=~\"$category\",severity=~\"$severity\"}\n) by (cluster_name)",
          "instant": true,
          "interval": "",
          "legendFormat": "{{alertname}}",
          "refId": "A"
        }
      ],
      "title": "Active Alerts by Cluster",
      "type": "piechart"
    },
    {
      "datasource": {
        "type": "prometheus",
        "uid": "${datasource}"
      },
      "description": "",
      "fieldConfig": {
        "defaults": {
          "color": {
            "mode": "palette-classic"
          },
          "custom": {
            "axisLabel": "",
            "axisPlacement": "auto",
            "barAlignment": 0,
            "drawStyle": "line",
            "fillOpacity": 0,
            "gradientMode": "none",
            "hideFrom": {
              "legend": false,
              "tooltip": false,
              "viz": false
            },
            "lineInterpolation": "linear",
            "lineWidth": 1,
            "pointSize": 5,
            "scaleDistribution": {
              "type": "linear"
            },
            "showPoints": "never",
            "spanNulls": true,
            "stacking": {
              "group": "A",
              "mode": "none"
            },
            "thresholdsStyle": {
              "mode": "off"
            }
          },
          "mappings": [],
          "thresholds": {
            "mode": "absolute",
            "steps": [
              {
                "color": "green",
                "value": null
              }
            ]
          }
        },
        "overrides": []
      },
      "gridPos": {
        "h": 8,
        "w": 12,
        "x": 0,
        "y": 9
      },
      "id": 310,
      "options": {
        "legend": {
          "calcs": [],
          "displayMode": "list",
          "placement": "bottom"
        },
        "tooltip": {
          "mode": "multi",
          "sort": "none"
        }
      },
      "pluginVersion": "8.4.2",
      "targets": [
        {
          "datasource": {
            "type": "prometheus",
            "uid": "$datasource"
          },
          "exemplar": true,
          "expr": "sum by (alertname) (\n    ALERTS{alertstate=\"firing\",cluster_name=~\"$cluster_name\",category=~\"$category\",severity=~\"$severity\"}\n    or\n    ALERTS{alertstate=\"firing\",instance=~\"$node\",category=~\"$category\",severity=~\"$severity\"}\n)",
          "hide": false,
          "instant": false,
          "interval": "",
          "intervalFactor": 1,
          "legendFormat": "{{alertstate}}",
          "refId": "B"
        }
      ],
      "title": "Alerts by Type ",
      "type": "timeseries"
    },
    {
      "datasource": {
        "type": "prometheus",
        "uid": "${datasource}"
      },
      "description": "",
      "fieldConfig": {
        "defaults": {
          "color": {
            "mode": "palette-classic"
          },
          "custom": {
            "axisLabel": "",
            "axisPlacement": "auto",
            "barAlignment": 0,
            "drawStyle": "line",
            "fillOpacity": 0,
            "gradientMode": "none",
            "hideFrom": {
              "legend": false,
              "tooltip": false,
              "viz": false
            },
            "lineInterpolation": "linear",
            "lineWidth": 1,
            "pointSize": 5,
            "scaleDistribution": {
              "type": "linear"
            },
            "showPoints": "never",
            "spanNulls": true,
            "stacking": {
              "group": "A",
              "mode": "none"
            },
            "thresholdsStyle": {
              "mode": "off"
            }
          },
          "mappings": [],
          "thresholds": {
            "mode": "absolute",
            "steps": [
              {
                "color": "green",
                "value": null
              }
            ]
          }
        },
        "overrides": []
      },
      "gridPos": {
        "h": 8,
        "w": 12,
        "x": 12,
        "y": 9
      },
      "id": 307,
      "options": {
        "legend": {
          "calcs": [],
          "displayMode": "list",
          "placement": "bottom"
        },
        "tooltip": {
          "mode": "multi",
          "sort": "none"
        }
      },
      "pluginVersion": "8.4.2",
      "targets": [
        {
          "datasource": {
            "type": "prometheus",
            "uid": "$datasource"
          },
          "exemplar": true,
          "expr": "sum by (alertstate) (\n    ALERTS{cluster_name=~\"$cluster_name\",category=~\"$category\",severity=~\"$severity\"}\n    or\n    ALERTS{instance=~\"$node\",category=~\"$category\",severity=~\"$severity\"}\n)",
          "hide": false,
          "instant": false,
          "interval": "",
          "intervalFactor": 1,
          "legendFormat": "{{alertstate}}",
          "refId": "B"
        }
      ],
      "title": "Alerts by State",
      "type": "timeseries"
    },
    {
      "datasource": {
        "type": "prometheus",
        "uid": "${datasource}"
      },
      "description": "",
      "fieldConfig": {
        "defaults": {
          "color": {
            "mode": "palette-classic"
          },
          "custom": {
            "axisLabel": "",
            "axisPlacement": "auto",
            "barAlignment": 0,
            "drawStyle": "line",
            "fillOpacity": 0,
            "gradientMode": "none",
            "hideFrom": {
              "legend": false,
              "tooltip": false,
              "viz": false
            },
            "lineInterpolation": "linear",
            "lineWidth": 1,
            "pointSize": 5,
            "scaleDistribution": {
              "type": "linear"
            },
            "showPoints": "never",
            "spanNulls": true,
            "stacking": {
              "group": "A",
              "mode": "none"
            },
            "thresholdsStyle": {
              "mode": "off"
            }
          },
          "mappings": [],
          "thresholds": {
            "mode": "absolute",
            "steps": [
              {
                "color": "green",
                "value": null
              }
            ]
          }
        },
        "overrides": []
      },
      "gridPos": {
        "h": 8,
        "w": 12,
        "x": 0,
        "y": 17
      },
      "id": 309,
      "options": {
        "legend": {
          "calcs": [],
          "displayMode": "list",
          "placement": "bottom"
        },
        "tooltip": {
          "mode": "single",
          "sort": "none"
        }
      },
      "pluginVersion": "8.4.2",
      "targets": [
        {
          "datasource": {
            "type": "prometheus",
            "uid": "$datasource"
          },
          "exemplar": true,
          "expr": "sum by (cluster_name) (\n    ALERTS{alertstate=\"firing\",cluster_name=~\"$cluster_name\",category=~\"$category\",severity=~\"$severity\"}\n)",
          "hide": false,
          "instant": false,
          "interval": "",
          "intervalFactor": 1,
          "legendFormat": "{{cluster_name}}",
          "refId": "B"
        }
      ],
      "title": "Alerts by Cluster ",
      "type": "timeseries"
    },
    {
      "datasource": {
        "type": "prometheus",
        "uid": "${datasource}"
      },
      "description": "",
      "fieldConfig": {
        "defaults": {
          "color": {
            "mode": "palette-classic"
          },
          "custom": {
            "axisLabel": "",
            "axisPlacement": "auto",
            "barAlignment": 0,
            "drawStyle": "line",
            "fillOpacity": 0,
            "gradientMode": "none",
            "hideFrom": {
              "legend": false,
              "tooltip": false,
              "viz": false
            },
            "lineInterpolation": "linear",
            "lineWidth": 1,
            "pointSize": 5,
            "scaleDistribution": {
              "type": "linear"
            },
            "showPoints": "never",
            "spanNulls": true,
            "stacking": {
              "group": "A",
              "mode": "none"
            },
            "thresholdsStyle": {
              "mode": "off"
            }
          },
          "mappings": [],
          "thresholds": {
            "mode": "absolute",
            "steps": [
              {
                "color": "green",
                "value": null
              }
            ]
          }
        },
        "overrides": []
      },
      "gridPos": {
        "h": 8,
        "w": 12,
        "x": 12,
        "y": 17
      },
      "id": 311,
      "options": {
        "legend": {
          "calcs": [],
          "displayMode": "list",
          "placement": "bottom"
        },
        "tooltip": {
          "mode": "multi",
          "sort": "none"
        }
      },
      "pluginVersion": "8.4.2",
      "targets": [
        {
          "datasource": {
            "type": "prometheus",
            "uid": "$datasource"
          },
          "exemplar": true,
          "expr": "sum by (category) (\n    ALERTS{alertstate=\"firing\",cluster_name=~\"$cluster_name\",category=~\"$category\",severity=~\"$severity\"}\n    or\n    ALERTS{alertstate=\"firing\",instance=~\"$node\",category=~\"$category\",severity=~\"$severity\"}\n)",
          "hide": false,
          "instant": false,
          "interval": "",
          "intervalFactor": 1,
          "legendFormat": "{{category}}",
          "refId": "B"
        }
      ],
      "title": "Alerts by Category ",
      "type": "timeseries"
    },
    {
      "datasource": {
        "type": "prometheus",
        "uid": "${datasource}"
      },
      "fieldConfig": {
        "defaults": {
          "color": {
            "mode": "thresholds"
          },
          "custom": {
            "align": "auto",
            "displayMode": "auto",
            "filterable": true
          },
          "mappings": [],
          "thresholds": {
            "mode": "absolute",
            "steps": [
              {
                "color": "green",
                "value": null
              },
              {
                "color": "red",
                "value": 80
              }
            ]
          }
        },
        "overrides": [
          {
            "matcher": {
              "id": "byName",
              "options": "Firing For"
            },
            "properties": [
              {
                "id": "unit",
                "value": "s"
              }
            ]
          },
          {
            "matcher": {
              "id": "byName",
              "options": "Alert"
            },
            "properties": [
              {
                "id": "custom.width",
                "value": 400
              }
            ]
          },
          {
            "matcher": {
              "id": "byName",
              "options": "Severity"
            },
            "properties": [
              {
                "id": "custom.width",
                "value": 80
              },
              {
                "id": "mappings",
                "value": [
                  {
                    "options": {
                      "critical": {
                        "color": "red",
                        "index": 2,
                        "text": "Critical"
                      },
                      "info": {
                        "color": "blue",
                        "index": 0,
                        "text": "Info"
                      },
                      "warning": {
                        "color": "yellow",
                        "index": 1,
                        "text": "Warning"
                      }
                    },
                    "type": "value"
                  }
                ]
              },
              {
                "id": "custom.displayMode",
                "value": "color-background-solid"
              }
            ]
          },
          {
            "matcher": {
              "id": "byName",
              "options": "Cluster Name"
            },
            "properties": [
              {
                "id": "noValue",
                "value": "N/A"
              }
            ]
          },
          {
            "matcher": {
              "id": "byName",
              "options": "Node"
            },
            "properties": [
              {
                "id": "noValue",
                "value": "N/A"
              }
            ]
          }
        ]
      },
      "gridPos": {
        "h": 9,
        "w": 24,
        "x": 0,
        "y": 25
      },
      "id": 303,
      "options": {
        "footer": {
          "fields": "",
          "reducer": [
            "sum"
          ],
          "show": false
        },
        "showHeader": true,
        "sortBy": []
      },
      "pluginVersion": "8.4.2",
      "targets": [
        {
          "datasource": {
            "type": "prometheus",
            "uid": "$datasource"
          },
          "exemplar": false,
          "expr": "count(\n    ALERTS{alertstate=\"firing\",cluster_name=~\"$cluster_name\",category=~\"$category\",severity=~\"$severity\"}\n    or\n    ALERTS{alertstate=\"firing\",instance=~\"$node\",category=~\"$category\",severity=~\"$severity\"}\n) by (alertname, cluster_name, instance, category, severity)",
          "format": "table",
          "instant": true,
          "interval": "",
          "legendFormat": "Alerts Count",
          "refId": "A"
        },
        {
          "datasource": {
            "type": "prometheus",
            "uid": "$datasource"
          },
          "exemplar": false,
          "expr": "max(\n    time() - ALERTS_FOR_STATE{cluster_name=~\"$cluster_name\",category=~\"$category\",severity=~\"$severity\"}\n    or  \n    time() - ALERTS_FOR_STATE{instance=~\"$node\",category=~\"$category\",severity=~\"$severity\"}\n) by (alertname, cluster_name, instance, category, severity)",
          "format": "table",
          "hide": false,
          "instant": true,
          "interval": "",
          "legendFormat": "Alerting For",
          "refId": "B"
        }
      ],
      "title": "Alerts Overview",
      "transformations": [
        {
          "id": "labelsToFields",
          "options": {}
        },
        {
          "id": "merge",
          "options": {}
        },
        {
          "id": "groupBy",
          "options": {
            "fields": {
              "Value #A": {
                "aggregations": [
                  "lastNotNull"
                ],
                "operation": "aggregate"
              },
              "Value #B": {
                "aggregations": [
                  "max"
                ],
                "operation": "aggregate"
              },
              "alertname": {
                "aggregations": [],
                "operation": "groupby"
              },
              "category": {
                "aggregations": [],
                "operation": "groupby"
              },
              "cluster_name": {
                "aggregations": [],
                "operation": "groupby"
              },
              "instance": {
                "aggregations": [],
                "operation": "groupby"
              },
              "severity": {
                "aggregations": [],
                "operation": "groupby"
              }
            }
          }
        },
        {
          "id": "organize",
          "options": {
            "excludeByName": {},
            "indexByName": {
              "Value #A (lastNotNull)": 5,
              "Value #B (max)": 6,
              "alertname": 0,
              "category": 2,
              "cluster_name": 3,
              "instance": 4,
              "severity": 1
            },
            "renameByName": {
              "Value #A (lastNotNull)": "Instances",
              "Value #B (max)": "Firing For",
              "alertname": "Alert",
              "category": "Category",
              "cluster_name": "Cluster Name",
              "instance": "Node",
              "severity": "Severity"
            }
          }
        },
        {
          "id": "filterByValue",
          "options": {
            "filters": [
              {
                "config": {
                  "id": "isNull",
                  "options": {}
                },
                "fieldName": "Instances"
              }
            ],
            "match": "all",
            "type": "exclude"
          }
        },
        {
          "id": "sortBy",
          "options": {
            "fields": {},
            "sort": [
              {
                "desc": true,
                "field": "Instances"
              }
            ]
          }
        }
      ],
      "type": "table"
    }
  ],
  "refresh": "30s",
  "schemaVersion": 35,
  "style": "dark",
  "tags": [
    "prometheus",
    "alerts",
    "alerting"
  ],
  "templating": {
    "list": [
      {
        "current": {
          "selected": false,
          "text": "",
          "value": ""
        },
        "hide": 0,
        "includeAll": false,
        "label": "Datasource",
        "multi": false,
        "name": "datasource",
        "options": [],
        "query": "prometheus",
        "refresh": 1,
        "regex": "",
        "skipUrlSync": false,
        "type": "datasource"
      },
      {
        "current": {
          "selected": true,
          "text": [
            "All"
          ],
          "value": [
            "$__all"
          ]
        },
        "datasource": {
          "type": "prometheus",
          "uid": "$datasource"
        },
        "definition": "label_values(ALERTS, cluster_name)",
        "hide": 0,
        "includeAll": true,
        "label": "Cluster",
        "multi": true,
        "name": "cluster_name",
        "options": [],
        "query": {
          "query": "label_values(ALERTS, cluster_name)",
          "refId": "StandardVariableQuery"
        },
        "refresh": 2,
        "regex": "",
        "skipUrlSync": false,
        "sort": 5,
        "tagValuesQuery": "",
        "tagsQuery": "",
        "type": "query",
        "useTags": false
      },
      {
        "current": {
          "selected": true,
          "text": [
            "All"
          ],
          "value": [
            "$__all"
          ]
        },
        "datasource": {
          "type": "prometheus",
          "uid": "$datasource"
        },
        "definition": "label_values(ALERTS, instance)",
        "hide": 0,
        "includeAll": true,
        "label": "Node",
        "multi": true,
        "name": "node",
        "options": [],
        "query": {
          "query": "label_values(ALERTS, instance)",
          "refId": "StandardVariableQuery"
        },
        "refresh": 2,
        "regex": "",
        "skipUrlSync": false,
        "sort": 5,
        "tagValuesQuery": "",
        "tagsQuery": "",
        "type": "query",
        "useTags": false
      },
      {
        "current": {
          "selected": true,
          "text": [
            "All"
          ],
          "value": [
            "$__all"
          ]
        },
        "datasource": {
          "type": "prometheus",
          "uid": "$datasource"
        },
        "definition": "label_values(ALERTS, category)",
        "hide": 0,
        "includeAll": true,
        "label": "Category",
        "multi": true,
        "name": "category",
        "options": [],
        "query": {
          "query": "label_values(ALERTS, category)",
          "refId": "StandardVariableQuery"
        },
        "refresh": 2,
        "regex": "",
        "skipUrlSync": false,
        "sort": 5,
        "tagValuesQuery": "",
        "tagsQuery": "",
        "type": "query",
        "useTags": false
      },
      {
        "current": {
          "selected": true,
          "text": [
            "All"
          ],
          "value": [
            "$__all"
          ]
        },
        "datasource": {
          "type": "prometheus",
          "uid": "$datasource"
        },
        "definition": "label_values(ALERTS, severity)",
        "hide": 0,
        "includeAll": true,
        "label": "Severity",
        "multi": true,
        "name": "severity",
        "options": [],
        "query": {
          "query": "label_values(ALERTS, severity)",
          "refId": "StandardVariableQuery"
        },
        "refresh": 2,
        "regex": "",
        "skipUrlSync": false,
        "sort": 5,
        "tagValuesQuery": "",
        "tagsQuery": "",
        "type": "query",
        "useTags": false
      }
    ]
  },
  "time": {
    "from": "now-30m",
    "to": "now"
  },
  "timepicker": {
    "refresh_intervals": [
      "15s",
      "30s",
      "1m",
      "5m",
      "15m",
      "30m",
      "1h",
      "2h",
      "1d"
    ],
    "time_options": [
      "5m",
      "15m",
      "1h",
      "6h",
      "12h",
      "24h",
      "2d",
      "7d",
      "30d"
    ]
  },
  "timezone": "",
  "title": "Prometheus Alerts",
  "uid": "2d94873f-5183-4233-ace6-d086ab528022",
  "version": 1,
  "weekStart": ""
}
